mkdocstrings_handlers/owa/__init__.py
mkdocstrings_handlers/owa/_internal/__init__.py
mkdocstrings_handlers/owa/_internal/config.py
mkdocstrings_handlers/owa/_internal/debug.py
mkdocstrings_handlers/owa/_internal/handler.py
mkdocstrings_handlers/owa/_internal/rendering.py
mkdocstrings_handlers/owa/config.py
mkdocstrings_handlers/owa/handler.py
mkdocstrings_handlers/owa/py.typed
mkdocstrings_handlers/owa/rendering.py
mkdocstrings_handlers/owa/templates/material/_base/attribute.html
mkdocstrings_handlers/owa/templates/material/_base/attribute.html.jinja
mkdocstrings_handlers/owa/templates/material/_base/backlinks.html.jinja
mkdocstrings_handlers/owa/templates/material/_base/children.html
mkdocstrings_handlers/owa/templates/material/_base/children.html.jinja
mkdocstrings_handlers/owa/templates/material/_base/class.html
mkdocstrings_handlers/owa/templates/material/_base/class.html.jinja
mkdocstrings_handlers/owa/templates/material/_base/docstring.html
mkdocstrings_handlers/owa/templates/material/_base/docstring.html.jinja
mkdocstrings_handlers/owa/templates/material/_base/docstring/admonition.html
mkdocstrings_handlers/owa/templates/material/_base/docstring/admonition.html.jinja
mkdocstrings_handlers/owa/templates/material/_base/docstring/attributes.html
mkdocstrings_handlers/owa/templates/material/_base/docstring/attributes.html.jinja
mkdocstrings_handlers/owa/templates/material/_base/docstring/classes.html
mkdocstrings_handlers/owa/templates/material/_base/docstring/classes.html.jinja
mkdocstrings_handlers/owa/templates/material/_base/docstring/examples.html
mkdocstrings_handlers/owa/templates/material/_base/docstring/examples.html.jinja
mkdocstrings_handlers/owa/templates/material/_base/docstring/functions.html
mkdocstrings_handlers/owa/templates/material/_base/docstring/functions.html.jinja
mkdocstrings_handlers/owa/templates/material/_base/docstring/modules.html
mkdocstrings_handlers/owa/templates/material/_base/docstring/modules.html.jinja
mkdocstrings_owa-1.16.12.post2.dist-info/METADATA
mkdocstrings_owa-1.16.12.post2.dist-info/WHEEL
mkdocstrings_owa-1.16.12.post2.dist-info/entry_points.txt
mkdocstrings_owa-1.16.12.post2.dist-info/licenses/LICENSE
mkdocstrings_owa-1.16.12.post2.dist-info/RECORD
