Metadata-Version: 2.4
Name: mkdocstrings-owa
Version: 1.16.12.post2
Summary: An OWA (Open World Agents) handler for mkdocstrings, with Python handler support.
Keywords: owa,open-world-agents,documentation,mkdocstrings
Author-Email: OWA Development Team <milkclouds00@gmail.com>
License-Expression: ISC
License-File: LICENSE
Classifier: Development Status :: 4 - Beta
Classifier: Intended Audience :: Developers
Classifier: Programming Language :: Python
Classifier: Programming Language :: Python :: 3
Classifier: Programming Language :: Python :: 3 :: Only
Classifier: Programming Language :: Python :: 3.9
Classifier: Programming Language :: Python :: 3.10
Classifier: Programming Language :: Python :: 3.11
Classifier: Programming Language :: Python :: 3.12
Classifier: Programming Language :: Python :: 3.13
Classifier: Programming Language :: Python :: 3.14
Classifier: Topic :: Documentation
Classifier: Topic :: Software Development
Classifier: Topic :: Software Development :: Documentation
Classifier: Topic :: Utilities
Classifier: Typing :: Typed
Project-URL: Homepage, https://github.com/open-world-agents/open-world-agents
Project-URL: Documentation, https://github.com/open-world-agents/open-world-agents
Project-URL: Repository, https://github.com/open-world-agents/open-world-agents
Project-URL: Issues, https://github.com/open-world-agents/open-world-agents/issues
Requires-Python: >=3.9
Requires-Dist: mkdocstrings>=0.28.3
Requires-Dist: mkdocs-autorefs>=1.4
Requires-Dist: griffe>=1.6.2
Requires-Dist: typing-extensions>=4.0; python_version < "3.11"
Requires-Dist: owa-core
